README.md
setup.py
pulumi_pulumistack/__init__.py
pulumi_pulumistack/_tables.py
pulumi_pulumistack/_utilities.py
pulumi_pulumistack/provider.py
pulumi_pulumistack/py.typed
pulumi_pulumistack/stack.py
pulumi_pulumistack.egg-info/PKG-INFO
pulumi_pulumistack.egg-info/SOURCES.txt
pulumi_pulumistack.egg-info/dependency_links.txt
pulumi_pulumistack.egg-info/not-zip-safe
pulumi_pulumistack.egg-info/requires.txt
pulumi_pulumistack.egg-info/top_level.txt