Metadata-Version: 2.1
Name: pulumi-pulumistack
Version: 0.0.1a1612923212
Summary: UNKNOWN
Home-page: UNKNOWN
License: UNKNOWN
Platform: UNKNOWN
